BruteText/__init__.py
BruteText/brutetext.py
BruteText-0.1.3.dist-info/LICENSE.md
BruteText-0.1.3.dist-info/METADATA
BruteText-0.1.3.dist-info/WHEEL
BruteText-0.1.3.dist-info/top_level.txt
BruteText-0.1.3.dist-info/RECORD
